gradio_mycomponent3/__init__.py
gradio_mycomponent3/mycomponent3.py
gradio_mycomponent3/mycomponent3.pyi
gradio_mycomponent3/templates/component/index.js
gradio_mycomponent3/templates/component/style.css
gradio_mycomponent3/templates/example/index.js
gradio_mycomponent3/templates/example/style.css
gradio_mycomponent3-0.0.2.dist-info/METADATA
gradio_mycomponent3-0.0.2.dist-info/WHEEL
gradio_mycomponent3-0.0.2.dist-info/RECORD
